menu/__init__.py
menu/_version.py
menu/admin.py
menu/apps.py
menu/auto_insert_group.py
menu/menus.py
menu/models.py
menu/tests.py
menu/urls.py
menu/views.py
menu/migrations/0001_initial.py
menu/migrations/0002_menugroup_kind.py
menu/migrations/0003_menu_is_new_alter_menu_link.py
menu/migrations/0004_alter_menu_menu_group.py
menu/migrations/0005_remove_menugroup_site_menugroup_group_and_more.py
menu/migrations/0006_alter_menugrouptranslation_unique_together_and_more.py
menu/migrations/0007_auto_20230130_1141.py
menu/migrations/0008_menu_exclude_menu.py
menu/migrations/0009_menu_is_initial_data.py
menu/migrations/__init__.py
menu/templates/index.html
menu/templates/test-menu.html
menu/templates/admin/parler/change_form.html
menu/templates/admin/parler/deletion_not_allowed.html
menu/templates/admin/parler/language_tabs.html
menu/templates/admin/parler/edit_inline/stacked_tabs.html
menu/templates/admin/parler/edit_inline/tabular_tabs.html
menu/templatetags/__init__.py
menu/templatetags/menu_tags.py
proj_menu/__init__.py
proj_menu/asgi.py
proj_menu/settings.py
proj_menu/urls.py
proj_menu/wsgi.py
authbox_menu-1.0.0.dist-info/LICENSE
authbox_menu-1.0.0.dist-info/METADATA
authbox_menu-1.0.0.dist-info/WHEEL
authbox_menu-1.0.0.dist-info/top_level.txt
authbox_menu-1.0.0.dist-info/RECORD
