Metadata-Version: 2.1
Name: authbox-menu
Version: 1.0.0
Summary: Auto create menu base on table values
Home-page: https://github.com/PROJECT-OUTBOX/authbox_menu.git
Author-email: suratiwan03@gmail.com
Keywords: menu,model base,environment,django
Classifier: License :: OSI Approved :: BSD License
Classifier: Intended Audience :: Developers
Classifier: Programming Language :: Python :: 3 :: Only
License-File: LICENSE
Requires-Dist: django-parler
Requires-Dist: authbox-setup-version
